teams/__init__.py
teams/activity_type.py
teams/adaptive_cards/__init__.py
teams/adaptive_cards/adaptive_cards.py
teams/adaptive_cards/adaptive_cards_options.py
teams/adaptive_cards/adaptive_cards_search_params.py
teams/adaptive_cards/adaptive_cards_search_result.py
teams/ai/__init__.py
teams/ai/actions/__init__.py
teams/ai/actions/action_entry.py
teams/ai/actions/action_turn_context.py
teams/ai/actions/action_types.py
teams/ai/ai.py
teams/ai/ai_options.py
teams/ai/augmentations/__init__.py
teams/ai/augmentations/augmentation.py
teams/ai/augmentations/default_augmentation.py
teams/ai/augmentations/monologue_augmentation.py
teams/ai/augmentations/sequence_augmentation.py
teams/ai/augmentations/tools_augmentation.py
teams/ai/citations/__init__.py
teams/ai/citations/citations.py
teams/ai/clients/__init__.py
teams/ai/clients/llm_client.py
teams/ai/data_sources/__init__.py
teams/ai/data_sources/data_source.py
teams/ai/data_sources/text_data_source.py
teams/ai/embeddings/__init__.py
teams/ai/embeddings/azure_openai_embeddings.py
teams/ai/embeddings/azure_openai_embeddings_options.py
teams/ai/embeddings/embeddings_model.py
teams/ai/embeddings/embeddings_response.py
teams/ai/embeddings/openai_embeddings.py
teams/ai/embeddings/openai_embeddings_options.py
teams/ai/models/__init__.py
teams/ai/models/chat_completion_action.py
teams/ai/models/openai_model.py
teams/ai/models/prompt_completion_model.py
teams/ai/models/prompt_completion_model_emitter.py
teams/ai/models/prompt_response.py
teams/ai/moderators/__init__.py
teams/ai/moderators/azure_content_safety_moderator.py
teams/ai/moderators/default_moderator.py
teams/ai/moderators/moderator.py
teams/ai/moderators/openai_moderator.py
teams/ai/planners/__init__.py
teams/ai/planners/action_planner.py
teams/ai/planners/assistants_planner.py
teams/ai/planners/plan.py
teams/ai/planners/planner.py
teams/ai/prompts/__init__.py
teams/ai/prompts/action_output_message.py
teams/ai/prompts/assistant_message.py
teams_ai-1.8.1.dist-info/entry_points.txt
teams_ai-1.8.1.dist-info/LICENSE
teams_ai-1.8.1.dist-info/METADATA
teams_ai-1.8.1.dist-info/WHEEL
teams_ai-1.8.1.dist-info/RECORD
