Metadata-Version: 2.3
Name: teams-ai
Version: 1.8.1
Summary: SDK focused on building AI based applications for Microsoft Teams.
Keywords: microsoft,teams,ai,bot
Author: Microsoft
Author-email: teams@microsoft.com
Requires-Python: >=3.9,<4.0
Classifier: Programming Language :: Python :: 3
Classifier: Programming Language :: Python :: 3.9
Classifier: Programming Language :: Python :: 3.10
Classifier: Programming Language :: Python :: 3.11
Classifier: Programming Language :: Python :: 3.12
Classifier: Programming Language :: Python :: 3.13
Requires-Dist: aiohttp (>=3.9.3,<4.0.0)
Requires-Dist: azure-ai-contentsafety (>=1.0.0,<2.0.0)
Requires-Dist: botbuilder-core (>=4.15.0,<5.0.0)
Requires-Dist: botbuilder-dialogs (>=4.14.8,<5.0.0)
Requires-Dist: botbuilder-integration-aiohttp (>=4.15.0,<5.0.0)
Requires-Dist: botframework-connector (>=4.15.0,<5.0.0)
Requires-Dist: dataclasses-json (>=0.6.4,<1.0.0)
Requires-Dist: jsonschema (>=4.21.1,<5.0.0)
Requires-Dist: msal (>=1.28.0,<2.0.0)
Requires-Dist: openai (>=v1.52.0,<v2.0.0)
Requires-Dist: pyyaml (>=6.0.1,<7.0.0)
Requires-Dist: tiktoken (>=0.7.0,<1.0.0)
Requires-Dist: types-pyyaml (>=6.0.12.12,<7.0.0.0)
Project-URL: Documentation, https://learn.microsoft.com/en-us/microsoftteams/platform/bots/how-to/teams%20conversational%20ai/teams-conversation-ai-overview
Project-URL: Repository, https://github.com/microsoft/teams-ai
